src/__init__.py
src/cli/__init__.py
src/cli/commands.py
src/config/__init__.py
src/config/config_loader.py
src/config/settings.py
src/core/__init__.py
src/core/async_processor.py
src/core/batch_processor.py
src/core/subtitle_gen.py
src/core/transcriber.py
src/core/video_processor.py
src/models/__init__.py
src/models/model_manager.py
src/utils/__init__.py
src/utils/downloader.py
src/utils/exceptions.py
src/utils/file_handler.py
src/utils/formatters.py
src/utils/validators.py
subtitle_generator-2.0.2.dist-info/licenses/LICENSE
subtitle_generator-2.0.2.dist-info/METADATA
subtitle_generator-2.0.2.dist-info/WHEEL
subtitle_generator-2.0.2.dist-info/entry_points.txt
subtitle_generator-2.0.2.dist-info/top_level.txt
subtitle_generator-2.0.2.dist-info/RECORD
