Metadata-Version: 2.4
Name: subtitle-generator
Version: 2.0.2
Summary: Open-source subtitle generation for seamless content translation.
Author-email: Ved Gupta <vedgupta@protonmail.com>
Maintainer-email: Ved Gupta <vedgupta@protonmail.com>
License: MIT
Project-URL: Homepage, https://github.com/innovatorved/subtitle
Project-URL: Documentation, https://github.com/innovatorved/subtitle#readme
Project-URL: Repository, https://github.com/innovatorved/subtitle.git
Project-URL: Issues, https://github.com/innovatorved/subtitle/issues
Project-URL: Changelog, https://github.com/innovatorved/subtitle/releases
Keywords: subtitle,transcription,whisper,ai,speech-to-text,video,audio,srt,vtt,innovatorved
Classifier: Development Status :: 4 - Beta
Classifier: Intended Audience :: Developers
Classifier: Intended Audience :: End Users/Desktop
Classifier: License :: OSI Approved :: MIT License
Classifier: Operating System :: OS Independent
Classifier: Programming Language :: Python :: 3
Classifier: Programming Language :: Python :: 3.9
Classifier: Programming Language :: Python :: 3.10
Classifier: Programming Language :: Python :: 3.11
Classifier: Programming Language :: Python :: 3.12
Classifier: Topic :: Multimedia :: Sound/Audio :: Speech
Classifier: Topic :: Multimedia :: Video
Classifier: Topic :: Scientific/Engineering :: Artificial Intelligence
Requires-Python: >=3.9
License-File: LICENSE
Requires-Dist: ffmpeg-python>=0.2.0
Requires-Dist: tqdm>=4.66.0
Requires-Dist: pyyaml>=6.0.0
Requires-Dist: gdown>=4.7.0
Provides-Extra: dev
Requires-Dist: pytest>=7.0.0; extra == "dev"
Requires-Dist: pytest-cov>=4.0.0; extra == "dev"
Requires-Dist: pytest-asyncio>=0.21.0; extra == "dev"
Requires-Dist: black>=23.0.0; extra == "dev"
Requires-Dist: isort>=5.0.0; extra == "dev"
Requires-Dist: mypy>=1.0.0; extra == "dev"
Requires-Dist: flake8>=6.0.0; extra == "dev"
Requires-Dist: build>=1.0.0; extra == "dev"
Requires-Dist: twine>=4.0.0; extra == "dev"
Dynamic: license-file
